cinema21.py
cinema21-1.0.1.dist-info/DESCRIPTION.rst
cinema21-1.0.1.dist-info/METADATA
cinema21-1.0.1.dist-info/RECORD
cinema21-1.0.1.dist-info/WHEEL
cinema21-1.0.1.dist-info/metadata.json
cinema21-1.0.1.dist-info/top_level.txt
