Metadata-Version: 2.0
Name: cinema21
Version: 1.0.1
Summary: A simple Cinema21 API wrapper.
Home-page: https://github.com/cwkfr/cinema21-py
Author: CWKFR
Author-email: cwkfr@protonmail.com
License: MIT
Project-URL: Bug Reports, https://github.com/cwkfr/cinema21-py/issues
Keywords: cinema21 unofficial api
Platform: UNKNOWN
Classifier: Development Status :: 5 - Production/Stable
Classifier: Intended Audience :: Developers
Classifier: Topic :: Games/Entertainment
Classifier: Topic :: Utilities
Classifier: Topic :: Software Development :: Libraries :: Python Modules
Classifier: License :: OSI Approved :: MIT License
Classifier: Programming Language :: Python :: 2.7
Classifier: Programming Language :: Python :: 3
Classifier: Programming Language :: Python :: 3.4
Classifier: Programming Language :: Python :: 3.5
Classifier: Programming Language :: Python :: 3.6
Requires-Dist: requests
